odoo/addons/account_invoice_supplier_date/README.rst
odoo/addons/account_invoice_supplier_date/__init__.py
odoo/addons/account_invoice_supplier_date/__manifest__.py
odoo/addons/account_invoice_supplier_date/i18n/account_invoice_supplier_date.pot
odoo/addons/account_invoice_supplier_date/i18n/es.po
odoo/addons/account_invoice_supplier_date/readme/CONTRIBUTORS.rst
odoo/addons/account_invoice_supplier_date/readme/DESCRIPTION.rst
odoo/addons/account_invoice_supplier_date/readme/USAGE.rst
odoo/addons/account_invoice_supplier_date/static/description/icon.png
odoo/addons/account_invoice_supplier_date/static/description/index.html
odoo/addons/account_invoice_supplier_date/views/account.xml
odoo12_addon_account_invoice_supplier_date-12.0.1.0.0.99.dev5.dist-info/METADATA
odoo12_addon_account_invoice_supplier_date-12.0.1.0.0.99.dev5.dist-info/WHEEL
odoo12_addon_account_invoice_supplier_date-12.0.1.0.0.99.dev5.dist-info/top_level.txt
odoo12_addon_account_invoice_supplier_date-12.0.1.0.0.99.dev5.dist-info/RECORD
